csv_diff_py-0.4.2.dist-info/licenses/LICENSE
csvdiff/cli.py
csvdiff/utils/csv.py
csvdiff/utils/files.py
csvdiff/utils/validation.py
csv_diff_py-0.4.2.dist-info/METADATA
csv_diff_py-0.4.2.dist-info/WHEEL
csv_diff_py-0.4.2.dist-info/entry_points.txt
csv_diff_py-0.4.2.dist-info/top_level.txt
csv_diff_py-0.4.2.dist-info/RECORD
