Metadata-Version: 2.4
Name: csv-diff-py
Version: 0.4.2
Summary: CLI tool for comparing CSV files in git diff format
Author-email: fityannugroho <fityannugroho@gmail.com>
Project-URL: Homepage, https://github.com/fityannugroho/csv-diff
Project-URL: Repository, https://github.com/fityannugroho/csv-diff
Project-URL: Changelog, https://github.com/fityannugroho/csv-diff/releases
Project-URL: Issues, https://github.com/fityannugroho/csv-diff/issues
Requires-Python: >=3.8
License-File: LICENSE
Requires-Dist: duckdb>=1.0.0
Requires-Dist: typer>=0.16.0
Dynamic: license-file
